annotatee/__init__.py
annotatee/__main__.py
annotatee/annotate.py
annotatee/main.py
annotatee/run.py
annotatee-0.0.1.data/data/LICENSE
annotatee-0.0.1.dist-info/LICENSE
annotatee-0.0.1.dist-info/METADATA
annotatee-0.0.1.dist-info/WHEEL
annotatee-0.0.1.dist-info/entry_points.txt
annotatee-0.0.1.dist-info/top_level.txt
annotatee-0.0.1.dist-info/RECORD
