Metadata-Version: 2.1
Name: annotatee
Version: 0.0.1
Home-page: https://github.com/ArianeMora/annotate-e
Author: Ariane Mora
Author-email: ariane.n.mora@gmail.com
License: GPL3
Project-URL: Bug Tracker, https://github.com/ArianeMora/annotate-e/issues
Project-URL: Documentation, https://github.com/ArianeMora/annotate-e
Project-URL: Source Code, https://github.com/ArianeMora/annotate-e
Keywords: gene-annotation,bioinformatics
Classifier: Intended Audience :: Science/Research
Classifier: License :: OSI Approved :: GNU General Public License v3 (GPLv3)
Classifier: Natural Language :: English
Classifier: Operating System :: OS Independent
Classifier: Programming Language :: Python :: 3.6
Classifier: Programming Language :: Python :: 3.7
Classifier: Programming Language :: Python :: 3.8
Classifier: Topic :: Scientific/Engineering :: Bio-Informatics
Requires-Python: >=3.10
License-File: LICENSE
Requires-Dist: pandas
Requires-Dist: numpy
Requires-Dist: enzymetk
Requires-Dist: sciutil >=1.0.3
Requires-Dist: sciviso
Requires-Dist: seaborn
Requires-Dist: typer
